ahocorasick_ner/__init__.py
ahocorasick_ner/datasets.py
ahocorasick_ner/opm.py
ahocorasick_ner/version.py
ahocorasick_ner-0.1.1.dist-info/METADATA
ahocorasick_ner-0.1.1.dist-info/WHEEL
ahocorasick_ner-0.1.1.dist-info/entry_points.txt
ahocorasick_ner-0.1.1.dist-info/top_level.txt
ahocorasick_ner-0.1.1.dist-info/RECORD
